smodels/__init__.py
smodels/installation.py
smodels/particles.py
smodels/version
smodels/etc/logging.conf
smodels/etc/logging_consoleonly.conf
smodels/etc/logging_file.conf
smodels/etc/parameters_default.ini
smodels/etc/pythia.card
smodels/etc/pythia8.cfg
smodels/experiment/__init__.py
smodels/experiment/databaseObj.py
smodels/experiment/datasetObj.py
smodels/experiment/exceptions.py
smodels/experiment/expResultObj.py
smodels/experiment/infoObj.py
smodels/experiment/metaObj.py
smodels/experiment/txnameObj.py
smodels/lib/Makefile
smodels/lib/nllfast/Makefile
smodels/lib/nllfast/nllfast-1.2/Makefile
smodels/lib/nllfast/nllfast-1.2/gdcpl_nllnlo_cteq6.grid
smodels/lib/nllfast/nllfast-1.2/gdcpl_nllnlo_mstw2008.grid
smodels/lib/nllfast/nllfast-1.2/gg_nllnlo_cteq6.grid
smodels/lib/nllfast/nllfast-1.2/gg_nllnlo_hm_cteq6.grid
smodels/lib/nllfast/nllfast-1.2/gg_nllnlo_hm_mstw2008.grid
smodels/lib/nllfast/nllfast-1.2/gg_nllnlo_mstw2008.grid
smodels/lib/nllfast/nllfast-1.2/nllfast-1.2.f
smodels/lib/nllfast/nllfast-1.2/sb_nllnlo_cteq6.grid
smodels/lib/nllfast/nllfast-1.2/sb_nllnlo_mstw2008.grid
smodels/lib/nllfast/nllfast-1.2/sdcpl_nllnlo_cteq6.grid
smodels/lib/nllfast/nllfast-1.2/sdcpl_nllnlo_mstw2008.grid
smodels/lib/nllfast/nllfast-1.2/sg_nllnlo_cteq6.grid
smodels/lib/nllfast/nllfast-1.2/sg_nllnlo_hm_cteq6.grid
smodels/lib/nllfast/nllfast-1.2/sg_nllnlo_hm_mstw2008.grid
smodels/lib/nllfast/nllfast-1.2/sg_nllnlo_mstw2008.grid
smodels/lib/nllfast/nllfast-1.2/ss_nllnlo_cteq6.grid
smodels/lib/nllfast/nllfast-1.2/ss_nllnlo_mstw2008.grid
smodels/lib/nllfast/nllfast-1.2/st_nllnlo_cteq6.grid
smodels/lib/nllfast/nllfast-1.2/st_nllnlo_mstw2008.grid
smodels/lib/nllfast/nllfast-1.2/tot_nllnlo_cteq6.grid
smodels/lib/nllfast/nllfast-1.2/tot_nllnlo_mstw2008.grid
smodels/lib/nllfast/nllfast-2.1/Makefile
smodels/lib/nllfast/nllfast-2.1/gdcpl_nllnlo_cteq6.grid
smodels/lib/nllfast/nllfast-2.1/gdcpl_nllnlo_mstw2008.grid
smodels-1.1.1.post2.dist-info/DESCRIPTION.rst
smodels-1.1.1.post2.dist-info/METADATA
smodels-1.1.1.post2.dist-info/RECORD
smodels-1.1.1.post2.dist-info/WHEEL
smodels-1.1.1.post2.dist-info/entry_points.txt
smodels-1.1.1.post2.dist-info/metadata.json
smodels-1.1.1.post2.dist-info/top_level.txt
