Metadata-Version: 2.0
Name: smodels
Version: 1.1.1.post2
Summary: A tool for interpreting simplified-model results from the LHC
Home-page: http://smodels.hephy.at/
Author: Federico Ambrogi, Sabine Kraml, Suchita Kulkarni, Ursula Laa, Andre Lessa, Veronika Magerl, Wolfgang Magerl, Doris Proschofsky, Michael Traub, Jory Sonneveld, Wolfgang Waltenberger
Author-email: smodels-developers@lists.oeaw.ac.at 
License: GPLv3
Keywords: simplified models LHC BSM theories interpretation supersymmetry UEDs
Platform: UNKNOWN
Classifier: Development Status :: 5 - Production/Stable
Classifier: Topic :: Scientific/Engineering :: Physics
Classifier: License :: OSI Approved :: GNU General Public License v3 (GPLv3)
Requires-Dist: argparse
Requires-Dist: docutils (>=0.3)
Requires-Dist: numpy
Requires-Dist: pyslha (>=3.1.0)
Requires-Dist: scipy
Requires-Dist: scipy (>=0.9.0)
Requires-Dist: unum
